pyswisslib.py
pyswisslib-1.0.1.dist-info/METADATA
pyswisslib-1.0.1.dist-info/WHEEL
pyswisslib-1.0.1.dist-info/top_level.txt
pyswisslib-1.0.1.dist-info/RECORD
